{"cameraMode":{"drawMode":0,"name":"Shaded","section":"Shading Mode"},"sceneLighting":true,"audioPlay":false,"sceneViewState":{"showFog":true,"showMaterialUpdate":false,"showSkybox":true,"showFlares":true,"showImageEffects":true,"showParticleSystems":true},"in2DMode":false,"pivot":{"x":-2.3234987258911135,"y":3.8821232318878176,"z":-2.775656223297119},"rotation":{"x":-0.07459285110235214,"y":-0.704645037651062,"z":0.07490945607423783,"w":-0.7016863226890564},"size":4.707949638366699,"orthographic":false}